setup.cfg
setup.py
pydataportability/__init__.py
pydataportability.microformats.xfn.egg-info/PKG-INFO
pydataportability.microformats.xfn.egg-info/SOURCES.txt
pydataportability.microformats.xfn.egg-info/dependency_links.txt
pydataportability.microformats.xfn.egg-info/entry_points.txt
pydataportability.microformats.xfn.egg-info/namespace_packages.txt
pydataportability.microformats.xfn.egg-info/not-zip-safe
pydataportability.microformats.xfn.egg-info/paster_plugins.txt
pydataportability.microformats.xfn.egg-info/requires.txt
pydataportability.microformats.xfn.egg-info/top_level.txt
pydataportability/microformats/__init__.py
pydataportability/microformats/xfn/__init__.py
pydataportability/microformats/xfn/config.py
pydataportability/microformats/xfn/xfn.py
