Metadata-Version: 1.0
Name: pydataportability.microformats.xfn
Version: 0.1dev-r19
Summary: an XFN parser for the microformats package
Home-page: http://mrtopf.de/blog
Author: Christian Scholz
Author-email: cs@comlounge.net
License: LGPL
Keywords: microformats dataportability xfn parser web
Platform: UNKNOWN
Classifier: Framework :: Plone
Classifier: Framework :: Zope2
Classifier: Framework :: Zope3
Classifier: Programming Language :: Python
Classifier: Topic :: Software Development :: Libraries :: Python Modules
